{
  "persons": [
    {
      "name": "Dan Abramov",
      "number": "12-43-234345",
      "id": 3
    },
    {
      "name": "Jhonatan",
      "number": "00000",
      "id": 6
    },
    {
      "name": "Testing adding notes",
      "number": "1230",
      "id": 7
    },
    {
      "name": "Jhonatan Nuñez",
      "number": "123455",
      "id": 8
    },
    {
      "name": "can i delete this note?",
      "number": "123",
      "id": 9
    },
    {
      "name": "Ada",
      "number": 0,
      "id": 10
    },
    {
      "name": "jhon",
      "number": "123",
      "id": 11
    },
    {
      "name": "jhon123",
      "number": "123",
      "id": 12
    }
  ]
}